<?xml version="1.0" encoding="UTF-8"?>
<objects serializationModel="Studio.02.02.00">
	<object class="AudioFile" id="{18193bd8-89b3-4e26-bee1-be37b0279b71}">
		<property name="assetPath">
			<value>HitRock 6095_59_2.wav</value>
		</property>
		<property name="frequencyInKHz">
			<value>48</value>
		</property>
		<property name="channelCount">
			<value>2</value>
		</property>
		<property name="length">
			<value>0.69333333333333336</value>
		</property>
		<relationship name="masterAssetFolder">
			<destination>{56cf1731-4433-496f-9709-d4dc8673799c}</destination>
		</relationship>
	</object>
</objects>
