<?xml version="1.0" encoding="UTF-8"?>
<objects serializationModel="Studio.02.02.00">
	<object class="AudioFile" id="{3b789fd3-7478-4882-95ee-a2d066b3992d}">
		<property name="assetPath">
			<value>GongIndian 6038_55_3.wav</value>
		</property>
		<property name="frequencyInKHz">
			<value>48</value>
		</property>
		<property name="channelCount">
			<value>2</value>
		</property>
		<property name="length">
			<value>3.7013333333333334</value>
		</property>
		<relationship name="masterAssetFolder">
			<destination>{56cf1731-4433-496f-9709-d4dc8673799c}</destination>
		</relationship>
	</object>
</objects>
